[{"features": [{"geometry": {"y": 4540729.844593409, "x": -13624870.150123741}, "attributes": {"Accident_t": "Pedestrian vs LRV", "Death_Reas": "Pending", "Inclusion_": "Y", "PrivatePrp": "N", "Time_accid": "0510", "OBJECTID": 17, "Date_accid": 1410134400000, "Time_death": "1638", "Accident_L": "3rd St at Carrol Ave", "Freeway_YN": "N", "IncorpCity": "Y", "Age": 71, "Geocoded": "YES", "FID": 1, "Y": 37.725567, "X": -122.394291, "ID": 24, "Deceased": "Pedestrian", "Freewayram": "N", "Sex": "Male", "County": "SF", "Exclusion_": " ", "LRV_YN": "Y", "Date_death": 1410134400000, "Corrected_": "3rd St and Carrol Ave"}}, {"geometry": {"y": 4547621.696244534, "x": -13624380.344364252}, "attributes": {"Accident_t": "Pedestrian vs Motor Vehicle", "Death_Reas": "Pending", "Inclusion_": "Y", "PrivatePrp": "N", "Time_accid": "2131", "OBJECTID": 18, "Date_accid": 1414800000000, "Time_death": "2140", "Accident_L": "3rd St and Islais Channel", "Freeway_YN": "N", "IncorpCity": "Y", "Age": 21, "Geocoded": "YES", "FID": 2, "Y": 37.774519, "X": -122.389891, "ID": 25, "Deceased": "Pedestrian", "Freewayram": "N", "Sex": "Male", "County": "SF", "Exclusion_": " ", "LRV_YN": " ", "Date_death": 1414800000000, "Corrected_": "3rd and Cargo Way"}}, {"geometry": {"y": 4549176.0621935055, "x": -13625144.218710076}, "attributes": {"Accident_t": "Pedestrian vs Motor Vehicle", "Death_Reas": "Pending", "Inclusion_": "Y", "PrivatePrp": "N", "Time_accid": "UNK", "OBJECTID": 19, "Date_accid": 1417824000000, "Time_death": "0020", "Accident_L": "Folsom St and 2nd St", "Freeway_YN": "N", "IncorpCity": "Y", "Age": 59, "Geocoded": "YES", "FID": 3, "Y": 37.785555, "X": -122.396753, "ID": 51, "Deceased": "Pedestrian", "Freewayram": "N", "Sex": "Male", "County": "SF", "Exclusion_": " ", "LRV_YN": " ", "Date_death": 1419811200000, "Corrected_": " "}}, {"geometry": {"y": 4542071.296377482, "x": -13628692.470706169}, "attributes": {"Accident_t": "Pedestrian vs LRV", "Death_Reas": "Pending", "Inclusion_": "Y", "PrivatePrp": "N", "Time_accid": "2056", "OBJECTID": 20, "Date_accid": 1400976000000, "Time_death": "0440", "Accident_L": "1200 Block of San Jose Ave", "Freeway_YN": "N", "IncorpCity": "Y", "Age": 34, "Geocoded": "YES", "FID": 4, "Y": 37.73509771, "X": -122.42862749, "ID": 22, "Deceased": "Pedestrian", "Freewayram": "N", "Sex": "Male", "County": "SF", "Exclusion_": " ", "LRV_YN": "Y", "Date_death": 1402617600000, "Corrected_": "1200 San Jose Ave"}}, {"geometry": {"y": 4543933.470438206, "x": -13627034.089705275}, "attributes": {"Accident_t": "Motor Vehicle collision (solo)", "Death_Reas": "Pending", "Inclusion_": "Y", "PrivatePrp": "N", "Time_accid": "0224", "OBJECTID": 26, "Date_accid": 1399075200000, "Time_death": "1720", "Accident_L": "Folsom St and Caesar Chavez", "Freeway_YN": "N", "IncorpCity": "Y", "Age": 26, "Geocoded": "YES", "FID": 5, "Y": 37.748326, "X": -122.41373, "ID": 38, "Deceased": "Driver", "Freewayram": "N", "Sex": "Male", "County": "SF", "Exclusion_": " ", "LRV_YN": " ", "Date_death": 1399075200000, "Corrected_": "Folsom St and Caesar Chavez St"}}, {"geometry": {"y": 4542546.129858954, "x": -13624990.263854306}, "attributes": {"Accident_t": "Pedestrian vs Motor Vehicle", "Death_Reas": "Pending", "Inclusion_": "Y", "PrivatePrp": "N", "Time_accid": "0904", "OBJECTID": 27, "Date_accid": 1409184000000, "Time_death": "0921", "Accident_L": "Quint St and Newcomb Ave", "Freeway_YN": "N", "IncorpCity": "Y", "Age": 52, "Geocoded": "YES", "FID": 6, "Y": 37.738471, "X": -122.39537, "ID": 44, "Deceased": "Pedestrian", "Freewayram": "N", "Sex": "Male", "County": "SF", "Exclusion_": " ", "LRV_YN": " ", "Date_death": 1409184000000, "Corrected_": "Quint St and Newcomb Ave"}}, {"geometry": {"y": 4548870.269257739, "x": -13626603.839873357}, "attributes": {"Accident_t": "Motor Vehicle collision (solo)", "Death_Reas": "Pending", "Inclusion_": "Y", "PrivatePrp": "N", "Time_accid": "2350", "OBJECTID": 28, "Date_accid": 1415059200000, "Time_death": "0001", "Accident_L": "In front of 34 Turk St", "Freeway_YN": "N", "IncorpCity": "Y", "Age": 35, "Geocoded": "YES", "FID": 7, "Y": 37.783384, "X": -122.409865, "ID": 26, "Deceased": "Passenger", "Freewayram": "N", "Sex": "Male", "County": "SF", "Exclusion_": " ", "LRV_YN": " ", "Date_death": 1415145600000, "Corrected_": "34 Turk St"}}, {"geometry": {"y": 4542057.82429302, "x": -13635974.825927828}, "attributes": {"Accident_t": "Pedestrian vs Motor Vehicle", "Death_Reas": "Pending", "Inclusion_": "Y", "PrivatePrp": "N", "Time_accid": "UNK", "OBJECTID": 29, "Date_accid": 1391472000000, "Time_death": "1111", "Accident_L": "Sunset Blvd and  Yorba St", "Freeway_YN": "N", "IncorpCity": "Y", "Age": 78, "Geocoded": "YES", "FID": 8, "Y": 37.735002, "X": -122.494046, "ID": 32, "Deceased": "Pedestrian", "Freewayram": "N", "Sex": "Male", "County": "SF", "Exclusion_": " ", "LRV_YN": " ", "Date_death": 1391472000000, "Corrected_": "Sunset Blvd and  Yorba St"}}, {"geometry": {"y": 4548112.375325571, "x": -13627667.386288395}, "attributes": {"Accident_t": "Pedestrian vs Motor Vehicle", "Death_Reas": "Pending", "Inclusion_": "Y", "PrivatePrp": "N", "Time_accid": "1820", "OBJECTID": 30, "Date_accid": 1388793600000, "Time_death": "1830", "Accident_L": "In front of 240 Van Ness Ave", "Freeway_YN": "N", "IncorpCity": "Y", "Age": 38, "Geocoded": "YES", "FID": 9, "Y": 37.778003, "X": -122.419419, "ID": 30, "Deceased": "Pedestrian", "Freewayram": "N", "Sex": "Male", "County": "SF", "Exclusion_": " ", "LRV_YN": " ", "Date_death": 1389052800000, "Corrected_": "240 Van Ness Ave"}}, {"geometry": {"y": 4546322.578702062, "x": -13627704.121720357}, "attributes": {"Accident_t": "Pedestrian vs Motor Vehicle", "Death_Reas": "Pending", "Inclusion_": "Y", "PrivatePrp": "N", "Time_accid": "1349", "OBJECTID": 31, "Date_accid": 1414972800000, "Time_death": "1315", "Accident_L": "1984 Mission St", "Freeway_YN": "N", "IncorpCity": "Y", "Age": 64, "Geocoded": "YES", "FID": 10, "Y": 37.765294, "X": -122.419749, "ID": 47, "Deceased": "Pedestrian", "Freewayram": "N", "Sex": "Male", "County": "SF", "Exclusion_": " ", "LRV_YN": " ", "Date_death": 1414972800000, "Corrected_": "1984 Mission St"}}, {"geometry": {"y": 4548142.656221591, "x": -13627727.832771894}, "attributes": {"Accident_t": "Pedestrian vs Motor Vehicle", "Death_Reas": "Pending", "Inclusion_": "Y", "PrivatePrp": "N", "Time_accid": "0226", "OBJECTID": 32, "Date_accid": 1391558400000, "Time_death": "1020", "Accident_L": "Van Ness Ave and Grove St", "Freeway_YN": "N", "IncorpCity": "Y", "Age": 53, "Geocoded": "YES", "FID": 11, "Y": 37.778218, "X": -122.419962, "ID": 33, "Deceased": "Pedestrian", "Freewayram": "N", "Sex": "Male", "County": "SF", "Exclusion_": " ", "LRV_YN": " ", "Date_death": 1391644800000, "Corrected_": "Van Ness Ave and Grove St"}}, {"geometry": {"y": 4549454.959944278, "x": -13627938.226609493}, "attributes": {"Accident_t": "Motorcycle vs Motor Vehicle", "Death_Reas": "Pending", "Inclusion_": "Y", "PrivatePrp": "N", "Time_accid": "0149", "OBJECTID": 33, "Date_accid": 1404777600000, "Time_death": "0613", "Accident_L": "Van Ness Ave and Sutter St", "Freeway_YN": "N", "IncorpCity": "Y", "Age": 51, "Geocoded": "YES", "FID": 12, "Y": 37.787535, "X": -122.421852, "ID": 40, "Deceased": "Motorcyclist", "Freewayram": "N", "Sex": "Male", "County": "SF", "Exclusion_": " ", "LRV_YN": " ", "Date_death": 1404777600000, "Corrected_": "Van Ness Ave and Sutter St"}}, {"geometry": {"y": 4546670.120773676, "x": -13636846.234901758}, "attributes": {"Accident_t": "Motorcycle collision (solo)", "Death_Reas": "Pending", "Inclusion_": "Y", "PrivatePrp": "N", "Time_accid": "1714", "OBJECTID": 34, "Date_accid": 1392681600000, "Time_death": "1917", "Accident_L": "John F Kennedy Drive and Spreckels Lake Dr", "Freeway_YN": "N", "IncorpCity": "Y", "Age": 53, "Geocoded": "YES", "FID": 13, "Y": 37.767762, "X": -122.501874, "ID": 35, "Deceased": "Motorcyclist", "Freewayram": "N", "Sex": "Male", "County": "SF", "Exclusion_": " ", "LRV_YN": " ", "Date_death": 1392681600000, "Corrected_": "John F Kennedy Drive and Chain of Lakes Dr"}}, {"geometry": {"y": 4548939.7822035765, "x": -13626053.53041215}, "attributes": {"Accident_t": "Pedestrian vs Motor Vehicle", "Death_Reas": "Pending", "Inclusion_": "Y", "PrivatePrp": "N", "Time_accid": "2235", "OBJECTID": 35, "Date_accid": 1408060800000, "Time_death": "2350", "Accident_L": "In front of 833 Mission St", "Freeway_YN": "N", "IncorpCity": "Y", "Age": 2, "Geocoded": "YES", "FID": 14, "Y": 37.7838775182, "X": -122.404921486, "ID": 7, "Deceased": "Pedestrian", "Freewayram": "N", "Sex": "Female", "County": "SF", "Exclusion_": " ", "LRV_YN": " ", "Date_death": 1408060800000, "Corrected_": "833 Mission St"}}, {"geometry": {"y": 4543083.728807747, "x": -13628217.304572916}, "attributes": {"Accident_t": "Pedestrian vs Motor Vehicle", "Death_Reas": "Pending", "Inclusion_": "Y", "PrivatePrp": "N", "Time_accid": "UNK", "OBJECTID": 36, "Date_accid": 1399852800000, "Time_death": "0035", "Accident_L": "Dolores St and 30th St", "Freeway_YN": "N", "IncorpCity": "Y", "Age": 77, "Geocoded": "YES", "FID": 15, "Y": 37.74229, "X": -122.424359, "ID": 28, "Deceased": "Pedestrian", "Freewayram": "N", "Sex": "Male", "County": "SF", "Exclusion_": " ", "LRV_YN": " ", "Date_death": 1403136000000, "Corrected_": "Dolores St and 30th St"}}, {"geometry": {"y": 4551398.718564109, "x": -13628250.25514219}, "attributes": {"Accident_t": "Pedestrian vs Motor Vehicle", "Death_Reas": "Pending", "Inclusion_": "Y", "PrivatePrp": "N", "Time_accid": "0610", "OBJECTID": 37, "Date_accid": 1415232000000, "Time_death": "072", "Accident_L": "Lombard St and Van Ness Ave", "Freeway_YN": "N", "IncorpCity": "Y", "Age": 51, "Geocoded": "YES", "FID": 16, "Y": 37.801333, "X": -122.424655, "ID": 10, "Deceased": "Pedestrian", "Freewayram": "N", "Sex": "Female", "County": "SF", "Exclusion_": " ", "LRV_YN": " ", "Date_death": 1415232000000, "Corrected_": "Lombard St and Van Ness Ave"}}, {"geometry": {"y": 4548581.950382523, "x": -13627742.415625188}, "attributes": {"Accident_t": "Pedestrian vs Motor Vehicle", "Death_Reas": "Pending", "Inclusion_": "Y", "PrivatePrp": "N", "Time_accid": "2304", "OBJECTID": 38, "Date_accid": 1396742400000, "Time_death": "2311", "Accident_L": "In front of 600 Van Ness Ave", "Freeway_YN": "N", "IncorpCity": "Y", "Age": 72, "Geocoded": "YES", "FID": 17, "Y": 37.781337, "X": -122.420093, "ID": 37, "Deceased": "Pedestrian", "Freewayram": "N", "Sex": "Male", "County": "SF", "Exclusion_": " ", "LRV_YN": " ", "Date_death": 1396742400000, "Corrected_": "600 Van Ness Ave"}}, {"geometry": {"y": 4548865.339459017, "x": -13627456.992450794}, "attributes": {"Accident_t": "Pedestrian vs Motor Vehicle", "Death_Reas": "Pending", "Inclusion_": "Y", "PrivatePrp": "N", "Time_accid": "0047", "OBJECTID": 39, "Date_accid": 1414972800000, "Time_death": "0946", "Accident_L": "Larkin St and Eddy St", "Freeway_YN": "N", "IncorpCity": "Y", "Age": 54, "Geocoded": "YES", "FID": 18, "Y": 37.783349, "X": -122.417529, "ID": 46, "Deceased": "Pedestrian", "Freewayram": "N", "Sex": "Male", "County": "SF", "Exclusion_": " ", "LRV_YN": " ", "Date_death": 1414972800000, "Corrected_": "Larkin St and Eddy St"}}, {"geometry": {"y": 4550390.026221842, "x": -13628028.395397037}, "attributes": {"Accident_t": "Pedestrian vs Motor Vehicle", "Death_Reas": "Pending", "Inclusion_": "Y", "PrivatePrp": "N", "Time_accid": "0054", "OBJECTID": 40, "Date_accid": 1392163200000, "Time_death": "0100", "Accident_L": "2000 Block of Van Ness Ave", "Freeway_YN": "N", "IncorpCity": "Y", "Age": 35, "Geocoded": "YES", "FID": 19, "Y": 37.794173, "X": -122.422662, "ID": 34, "Deceased": "Pedestrian", "Freewayram": "N", "Sex": "Male", "County": "SF", "Exclusion_": " ", "LRV_YN": " ", "Date_death": 1392163200000, "Corrected_": "2000 Van Ness Ave"}}, {"geometry": {"y": 4550163.462854718, "x": -13626349.69179858}, "attributes": {"Accident_t": "Pedestrian vs Motor Vehicle", "Death_Reas": "Pending", "Inclusion_": "Y", "PrivatePrp": "N", "Time_accid": "0953", "OBJECTID": 41, "Date_accid": 1411171200000, "Time_death": "0955", "Accident_L": "In front of 770 Stockton St", "Freeway_YN": "N", "IncorpCity": "Y", "Age": 78, "Geocoded": "YES", "FID": 20, "Y": 37.79256469, "X": -122.407581949, "ID": 8, "Deceased": "Pedestrian", "Freewayram": "N", "Sex": "Female", "County": "SF", "Exclusion_": " ", "LRV_YN": " ", "Date_death": 1411171200000, "Corrected_": "770 Stockton St"}}, {"geometry": {"y": 4552410.467577479, "x": -13621821.88850735}, "attributes": {"Accident_t": "Motorcycle collision (solo)", "Death_Reas": "Pending", "Inclusion_": "Y", "PrivatePrp": "N", "Time_accid": "1300", "OBJECTID": 42, "Date_accid": 1418688000000, "Time_death": "1428", "Accident_L": "Treasure Island Road at Westbound I-80 onramp", "Freeway_YN": "N", "IncorpCity": "Y", "Age": 20, "Geocoded": "YES", "FID": 21, "Y": 37.808514, "X": -122.366908, "ID": 49, "Deceased": "Motorcyclist", "Freewayram": "Y", "Sex": "Male", "County": "SF", "Exclusion_": " ", "LRV_YN": " ", "Date_death": 1418688000000, "Corrected_": " "}}, {"geometry": {"y": 4549650.756264, "x": -13629270.38695582}, "attributes": {"Accident_t": "Pedestrian vs Motor Vehicle", "Death_Reas": "Pending", "Inclusion_": "Y", "PrivatePrp": "N", "Time_accid": "1510", "OBJECTID": 43, "Date_accid": 1392854400000, "Time_death": "1750", "Accident_L": "California St and Fillmore St", "Freeway_YN": "N", "IncorpCity": "Y", "Age": 90, "Geocoded": "YES", "FID": 22, "Y": 37.788925, "X": -122.433819, "ID": 5, "Deceased": "Pedestrian", "Freewayram": "N", "Sex": "Female", "County": "SF", "Exclusion_": " ", "LRV_YN": " ", "Date_death": 1392854400000, "Corrected_": "California St and Fillmore St"}}, {"geometry": {"y": 4548433.498150055, "x": -13627579.221251687}, "attributes": {"Accident_t": "Pedestrian vs Motor Vehicle", "Death_Reas": "Pending", "Inclusion_": "Y", "PrivatePrp": "N", "Time_accid": "1130", "OBJECTID": 44, "Date_accid": 1414022400000, "Time_death": "1246", "Accident_L": "Polk St and McAllister St", "Freeway_YN": "N", "IncorpCity": "Y", "Age": 68, "Geocoded": "YES", "FID": 23, "Y": 37.780283, "X": -122.418627, "ID": 9, "Deceased": "Pedestrian", "Freewayram": "N", "Sex": "Female", "County": "SF", "Exclusion_": " ", "LRV_YN": " ", "Date_death": 1414022400000, "Corrected_": "Polk St and McAllister St"}}, {"geometry": {"y": 4549237.7571129035, "x": -13630150.36753054}, "attributes": {"Accident_t": "Motorcycle vs Motor Vehicle", "Death_Reas": "Pending", "Inclusion_": "Y", "PrivatePrp": "N", "Time_accid": "UNK", "OBJECTID": 45, "Date_accid": 1389916800000, "Time_death": "1054", "Accident_L": "Broderick St and Bush St", "Freeway_YN": "N", "IncorpCity": "Y", "Age": 61, "Geocoded": "YES", "FID": 24, "Y": 37.785993, "X": -122.441724, "ID": 31, "Deceased": "Motorcyclist", "Freewayram": "N", "Sex": "Male", "County": "SF", "Exclusion_": " ", "LRV_YN": " ", "Date_death": 1390089600000, "Corrected_": "Broderick St and Bush St"}}, {"geometry": {"y": 4548996.472899873, "x": -13624608.104042418}, "attributes": {"Accident_t": "Bicycle collision (solo)", "Death_Reas": "Pending", "Inclusion_": "Y", "PrivatePrp": "N", "Time_accid": "1516", "OBJECTID": 46, "Date_accid": 1414022400000, "Time_death": "1405", "Accident_L": "In front of 301 Bryant St", "Freeway_YN": "N", "IncorpCity": "Y", "Age": 27, "Geocoded": "YES", "FID": 25, "Y": 37.78428, "X": -122.391937, "ID": 52, "Deceased": "Bicyclist", "Freewayram": "N", "Sex": "Male", "County": "SF", "Exclusion_": " ", "LRV_YN": " ", "Date_death": 1414022400000, "Corrected_": " "}}, {"geometry": {"y": 4546911.773555682, "x": -13627247.043891164}, "attributes": {"Accident_t": "Bicycle vs Motor Vehicle", "Death_Reas": "Pending", "Inclusion_": "Y", "PrivatePrp": "N", "Time_accid": "UNK", "OBJECTID": 47, "Date_accid": 1395187200000, "Time_death": "0025", "Accident_L": "Cross of 13th St and Folsom St", "Freeway_YN": "N", "IncorpCity": "Y", "Age": 55, "Geocoded": "YES", "FID": 26, "Y": 37.769478, "X": -122.415643, "ID": 36, "Deceased": "Bicyclist", "Freewayram": "N", "Sex": "Male", "County": "SF", "Exclusion_": " ", "LRV_YN": " ", "Date_death": 1395619200000, "Corrected_": "13th St and Folsom St"}}, {"geometry": {"y": 4542078.515935497, "x": -13636768.199938713}, "attributes": {"Accident_t": "Pedestrian vs Motor Vehicle", "Death_Reas": "Pending", "Inclusion_": "Y", "PrivatePrp": "N", "Time_accid": "0657", "OBJECTID": 48, "Date_accid": 1413763200000, "Time_death": "0720", "Accident_L": "Sloat Blvd and 43rd St", "Freeway_YN": "N", "IncorpCity": "Y", "Age": 87, "Geocoded": "YES", "FID": 27, "Y": 37.735149, "X": -122.501173, "ID": 45, "Deceased": "Pedestrian", "Freewayram": "N", "Sex": "Male", "County": "SF", "Exclusion_": " ", "LRV_YN": " ", "Date_death": 1413763200000, "Corrected_": "Sloat Blvd and 43rd St"}}, {"geometry": {"y": 4550499.6252085185, "x": -13628851.046434004}, "attributes": {"Accident_t": "Bicycle vs Motor Vehicle", "Death_Reas": "Pending", "Inclusion_": "Y", "PrivatePrp": "N", "Time_accid": "UNK", "OBJECTID": 49, "Date_accid": 1400976000000, "Time_death": "0640", "Accident_L": "Broadway St and Laguna St", "Freeway_YN": "N", "IncorpCity": "Y", "Age": 51, "Geocoded": "YES", "FID": 28, "Y": 37.794951, "X": -122.430052, "ID": 29, "Deceased": "Bicyclist", "Freewayram": "N", "Sex": "Male", "County": "SF", "Exclusion_": " ", "LRV_YN": " ", "Date_death": 1401840000000, "Corrected_": "Broadway St and Laguna St"}}, {"geometry": {"y": 4549478.624339778, "x": -13626995.573161459}, "attributes": {"Accident_t": "Pedestrian vs Motor Vehicle", "Death_Reas": "Pending", "Inclusion_": "Y", "PrivatePrp": "N", "Time_accid": "2218", "OBJECTID": 50, "Date_accid": 1406505600000, "Time_death": "1605", "Accident_L": "Post St and Jones St", "Freeway_YN": "N", "IncorpCity": "Y", "Age": 29, "Geocoded": "YES", "FID": 29, "Y": 37.787703, "X": -122.413384, "ID": 41, "Deceased": "Pedestrian", "Freewayram": "N", "Sex": "Male", "County": "SF", "Exclusion_": " ", "LRV_YN": " ", "Date_death": 1408147200000, "Corrected_": "Post St and Jones St"}}, {"geometry": {"y": 4543519.935918264, "x": -13625819.962973513}, "attributes": {"Accident_t": "Motor Vehicle collision (solo)", "Death_Reas": "Pending", "Inclusion_": "Y", "PrivatePrp": "N", "Time_accid": "1430", "OBJECTID": 51, "Date_accid": 1401926400000, "Time_death": "1650", "Accident_L": "In front of 128 Barnveld Ave", "Freeway_YN": "N", "IncorpCity": "Y", "Age": 30, "Geocoded": "YES", "FID": 30, "Y": 37.7453885875, "X": -122.402823314, "ID": 39, "Deceased": "Driver", "Freewayram": "N", "Sex": "Male", "County": "SF", "Exclusion_": " ", "LRV_YN": " ", "Date_death": 1401926400000, "Corrected_": "128 Barnceld Ave"}}, {"geometry": {"y": 4538605.569608529, "x": -13625971.322526673}, "attributes": {"Accident_t": "Pedestrian vs Motor Vehicle", "Death_Reas": "Pending", "Inclusion_": "Y", "PrivatePrp": "N", "Time_accid": "UNK", "OBJECTID": 52, "Date_accid": 1395273600000, "Time_death": "1121", "Accident_L": "Bayshore Blvd near Visitation Ave", "Freeway_YN": "N", "IncorpCity": "Y", "Age": 82, "Geocoded": "YES", "FID": 31, "Y": 37.710472, "X": -122.404183, "ID": 6, "Deceased": "Pedestrian", "Freewayram": "N", "Sex": "Female", "County": "SF", "Exclusion_": " ", "LRV_YN": " ", "Date_death": 1395273600000, "Corrected_": "Bayshore Blvd and Visitation Ave"}}], "fields": [{"domain": null, "name": "FID", "defaultValue": null, "alias": "FID", "sqlType": "sqlTypeInteger", "type": "esriFieldTypeInteger"}, {"domain": null, "name": "OBJECTID", "defaultValue": null, "alias": "OBJECTID", "sqlType": "sqlTypeInteger", "type": "esriFieldTypeInteger"}, {"domain": null, "name": "ID", "defaultValue": null, "alias": "ID", "sqlType": "sqlTypeFloat", "type": "esriFieldTypeDouble"}, {"domain": null, "name": "Age", "defaultValue": null, "alias": "Age", "sqlType": "sqlTypeFloat", "type": "esriFieldTypeDouble"}, {"domain": null, "name": "Sex", "defaultValue": null, "alias": "Sex", "length": 254, "sqlType": "sqlTypeNVarchar", "type": "esriFieldTypeString"}, {"domain": null, "name": "Date_death", "defaultValue": null, "alias": "Date_death", "length": 8, "sqlType": "sqlTypeTimestamp2", "type": "esriFieldTypeDate"}, {"domain": null, "name": "Time_death", "defaultValue": null, "alias": "Time_death", "length": 254, "sqlType": "sqlTypeNVarchar", "type": "esriFieldTypeString"}, {"domain": null, "name": "Date_accid", "defaultValue": null, "alias": "Date_accid", "length": 8, "sqlType": "sqlTypeTimestamp2", "type": "esriFieldTypeDate"}, {"domain": null, "name": "Time_accid", "defaultValue": null, "alias": "Time_accid", "length": 254, "sqlType": "sqlTypeNVarchar", "type": "esriFieldTypeString"}, {"domain": null, "name": "PrivatePrp", "defaultValue": null, "alias": "PrivatePrp", "length": 254, "sqlType": "sqlTypeNVarchar", "type": "esriFieldTypeString"}, {"domain": null, "name": "IncorpCity", "defaultValue": null, "alias": "IncorpCity", "length": 254, "sqlType": "sqlTypeNVarchar", "type": "esriFieldTypeString"}, {"domain": null, "name": "County", "defaultValue": null, "alias": "County", "length": 254, "sqlType": "sqlTypeNVarchar", "type": "esriFieldTypeString"}, {"domain": null, "name": "Accident_L", "defaultValue": null, "alias": "Accident_L", "length": 254, "sqlType": "sqlTypeNVarchar", "type": "esriFieldTypeString"}, {"domain": null, "name": "Corrected_", "defaultValue": null, "alias": "Corrected_", "length": 254, "sqlType": "sqlTypeNVarchar", "type": "esriFieldTypeString"}, {"domain": null, "name": "Deceased", "defaultValue": null, "alias": "Deceased", "length": 254, "sqlType": "sqlTypeNVarchar", "type": "esriFieldTypeString"}, {"domain": null, "name": "Death_Reas", "defaultValue": null, "alias": "Death_Reas", "length": 254, "sqlType": "sqlTypeNVarchar", "type": "esriFieldTypeString"}, {"domain": null, "name": "Accident_t", "defaultValue": null, "alias": "Accident_t", "length": 254, "sqlType": "sqlTypeNVarchar", "type": "esriFieldTypeString"}, {"domain": null, "name": "X", "defaultValue": null, "alias": "X", "sqlType": "sqlTypeFloat", "type": "esriFieldTypeDouble"}, {"domain": null, "name": "Y", "defaultValue": null, "alias": "Y", "sqlType": "sqlTypeFloat", "type": "esriFieldTypeDouble"}, {"domain": null, "name": "Geocoded", "defaultValue": null, "alias": "Geocoded", "length": 254, "sqlType": "sqlTypeNVarchar", "type": "esriFieldTypeString"}, {"domain": null, "name": "Freeway_YN", "defaultValue": null, "alias": "Freeway_YN", "length": 254, "sqlType": "sqlTypeNVarchar", "type": "esriFieldTypeString"}, {"domain": null, "name": "Inclusion_", "defaultValue": null, "alias": "Inclusion_", "length": 254, "sqlType": "sqlTypeNVarchar", "type": "esriFieldTypeString"}, {"domain": null, "name": "Exclusion_", "defaultValue": null, "alias": "Exclusion_", "length": 254, "sqlType": "sqlTypeNVarchar", "type": "esriFieldTypeString"}, {"domain": null, "name": "Freewayram", "defaultValue": null, "alias": "Freewayram", "length": 254, "sqlType": "sqlTypeNVarchar", "type": "esriFieldTypeString"}, {"domain": null, "name": "LRV_YN", "defaultValue": null, "alias": "LRV_YN", "length": 254, "sqlType": "sqlTypeNVarchar", "type": "esriFieldTypeString"}], "spatialReference": {"wkid": 102100, "latestWkid": 3857}, "geometryType": "esriGeometryPoint", "objectIdFieldName": "FID", "globalIdFieldName": ""}]
